skymap_overlap/_version.py
skymap_overlap/combine_skymaps.py
skymap_overlap/compute_overlap.py
skymap_overlap/compute_overlap_from_skymaps_pipe.py
skymap_overlap/download_skymap.py
skymap_overlap-0.1.6.dist-info/LICENSE
skymap_overlap-0.1.6.dist-info/METADATA
skymap_overlap-0.1.6.dist-info/WHEEL
skymap_overlap-0.1.6.dist-info/entry_points.txt
skymap_overlap-0.1.6.dist-info/top_level.txt
skymap_overlap-0.1.6.dist-info/RECORD
