Metadata-Version: 2.1
Name: skymap-overlap
Version: 0.1.6
Summary: Compute overlap between two skymaps
Home-page: https://git.ligo.org/ka-lok.lo/skymap-overlap
Author: Rico Ka Lok Lo
Author-email: ka-lok.lo@ligo.org
Requires-Python: >=3.9
License-File: LICENSE
Requires-Dist: healpy
Requires-Dist: ligo.skymap
Requires-Dist: pycondor
